{
  "transactions": [
    {
      "id": 1,
      "description": "Desenvolvimento de site",
      "type": "income",
      "category": "Venda",
      "price": 1400,
      "createdAt": "2022-09-27T16:54:49.564Z"
    },
    {
      "id": 2,
      "description": "Hamburger",
      "type": "outcome",
      "category": "Alimentação",
      "price": 40,
      "createdAt": "2022-09-27T16:54:15.564Z"
    },
    {
      "id": 3,
      "description": "Teclado Kronthon K2",
      "type": "outcome",
      "category": "Tecnologia",
      "price": 538,
      "createdAt": "2022-09-27T16:54:05.564Z"
    },
    {
      "description": "Desenvolvimento de APP",
      "price": 10000,
      "category": "Venda",
      "type": "income",
      "createdAt": "2022-09-28T13:41:12.231Z",
      "id": 4
    },
    {
      "description": "Chcolate Talento",
      "price": 8,
      "category": "Alimentação",
      "type": "outcome",
      "createdAt": "2022-09-28T13:56:28.339Z",
      "id": 5
    }
  ]
}